mpsops/__init__.py
mpsops-0.1.18.dist-info/METADATA
mpsops-0.1.18.dist-info/WHEEL
mpsops-0.1.18.dist-info/top_level.txt
mpsops-0.1.18.dist-info/RECORD
