Metadata-Version: 2.4
Name: mpsops
Version: 0.1.18
Summary: CUDA-only PyTorch operations for Apple Silicon - metapackage
Author: mpsops
License-Expression: MIT
Project-URL: Homepage, https://github.com/mpsops
Project-URL: Repository, https://github.com/mpsops/mpsops
Project-URL: Issues, https://github.com/mpsops/mpsops/issues
Keywords: pytorch,mps,apple-silicon,metal,gpu,machine-learning
Classifier: Development Status :: 4 - Beta
Classifier: Intended Audience :: Developers
Classifier: Intended Audience :: Science/Research
Classifier: Operating System :: MacOS :: MacOS X
Classifier: Programming Language :: Python :: 3
Classifier: Programming Language :: Python :: 3.10
Classifier: Programming Language :: Python :: 3.11
Classifier: Programming Language :: Python :: 3.12
Classifier: Topic :: Scientific/Engineering :: Artificial Intelligence
Requires-Python: >=3.10
Requires-Dist: torch>=2.0.0
Requires-Dist: mps-flash-attn>=0.2.3
Requires-Dist: mps-bitsandbytes>=0.4.8
Requires-Dist: mps-deform-conv>=0.1.4
Requires-Dist: mps-correlation>=0.1.4
Requires-Dist: mps-carafe>=0.1.4
Requires-Dist: mps-conv3d>=0.1.5
Provides-Extra: flash-attn
Requires-Dist: mps-flash-attn>=0.2.3; extra == "flash-attn"
Provides-Extra: bitsandbytes
Requires-Dist: mps-bitsandbytes>=0.4.8; extra == "bitsandbytes"
Provides-Extra: deform-conv
Requires-Dist: mps-deform-conv>=0.1.4; extra == "deform-conv"
Provides-Extra: correlation
Requires-Dist: mps-correlation>=0.1.4; extra == "correlation"
Provides-Extra: carafe
Requires-Dist: mps-carafe>=0.1.4; extra == "carafe"
Provides-Extra: conv3d
Requires-Dist: mps-conv3d>=0.1.5; extra == "conv3d"
